aioqueue/__init__.py
aioqueue/exceptions.py
aioqueue/logger.py
aioqueue/queue.py
aioqueue/response.py
aioqueue/task.py
aioqueue-0.3.0.dist-info/DESCRIPTION.rst
aioqueue-0.3.0.dist-info/METADATA
aioqueue-0.3.0.dist-info/RECORD
aioqueue-0.3.0.dist-info/WHEEL
aioqueue-0.3.0.dist-info/metadata.json
aioqueue-0.3.0.dist-info/top_level.txt
