Metadata-Version: 2.0
Name: aioqueue
Version: 0.3.0
Summary: A Python Task Queue library using RabbitMQ (aioamqp) and asyncio
Home-page: https://github.com/jjacobson93/aioqueue
Author: Jeremy Jacobson
Author-email: jjacobson93@gmail.com
License: MIT
Platform: UNKNOWN
Requires-Dist: aioamqp (==0.10.0)
Requires-Dist: u-msgpack-python (==2.4.1)
